fontinfo/__init__.py
fontinfo-0.1.1.dist-info/LICENSE
fontinfo-0.1.1.dist-info/METADATA
fontinfo-0.1.1.dist-info/WHEEL
fontinfo-0.1.1.dist-info/top_level.txt
fontinfo-0.1.1.dist-info/RECORD
